alchemica/__init__.py
alchemica/after_execute.py
alchemica/async_logger.py
alchemica/before_execute.py
alchemica/log_explain_plan.py
alchemica/sync_logger.py
alchemica/utils/__init__.py
alchemica/utils/default_logger.py
alchemica/utils/lock.py
alchemica/utils/sqlalchemy_patch.py
alchemica/utils/utils.py
alchemica-0.0.2.dev6.dist-info/LICENSE
alchemica-0.0.2.dev6.dist-info/METADATA
alchemica-0.0.2.dev6.dist-info/WHEEL
alchemica-0.0.2.dev6.dist-info/top_level.txt
alchemica-0.0.2.dev6.dist-info/RECORD
