Metadata-Version: 2.2
Name: alchemica
Version: 0.0.2.dev6
Summary: Alchemica — SQLAlchemy Logger with logging magic. Sync, async, multithreaded
Author-email: Grigoriy Gusev <thegrigus@gmail.com>
Project-URL: Homepage, https://github.com/gri-gus/alchemica
Project-URL: Source, https://github.com/gri-gus/alchemica
Keywords: sqlalchemy,sql alchemy,sql alchemy debugger,sqlalchemy debugger,sqlalchemy debug,sqlalchemy log,sqlalchemy logs,sqlalchemy logger,salo,alchemica
Classifier: Programming Language :: Python :: 3.10
Classifier: License :: OSI Approved :: Apache Software License
Classifier: Operating System :: OS Independent
Requires-Python: >=3.8
License-File: LICENSE
Requires-Dist: greenlet==3.1.1
Requires-Dist: SQLAlchemy>=2.0.0
Requires-Dist: typing_extensions>=4.5.0
